.gitignore
API.rst
MANIFEST.in
screenshot-small.png
screenshot.png
setup.py
stdeb.cfg
CamTrigUSB/.gitignore
CamTrigUSB/99-motmot-cam-trig.oldudev.rules
CamTrigUSB/99-motmot-cam-trig.rules
CamTrigUSB/LUFA.pnproj
CamTrigUSB/OVERVIEW.rst
CamTrigUSB/README-firmware.rst
CamTrigUSB/README.rst
CamTrigUSB/camtrig_example.jpg
CamTrigUSB/makefile
CamTrigUSB/teensy++-2.0.jpg
CamTrigUSB/usbkey.jpg
CamTrigUSB/wiring.png
CamTrigUSB/wiring.rst
CamTrigUSB/wiring.svg
CamTrigUSB/Bootloaders/makefile
CamTrigUSB/Bootloaders/CDC/BootloaderCDC.aps
CamTrigUSB/Bootloaders/CDC/BootloaderCDC.c
CamTrigUSB/Bootloaders/CDC/BootloaderCDC.h
CamTrigUSB/Bootloaders/CDC/BootloaderCDC.txt
CamTrigUSB/Bootloaders/CDC/Descriptors.c
CamTrigUSB/Bootloaders/CDC/Descriptors.h
CamTrigUSB/Bootloaders/CDC/Doxygen.conf
CamTrigUSB/Bootloaders/CDC/LUFA CDC Bootloader.inf
CamTrigUSB/Bootloaders/CDC/makefile
CamTrigUSB/Bootloaders/DFU/BootloaderDFU.aps
CamTrigUSB/Bootloaders/DFU/BootloaderDFU.c
CamTrigUSB/Bootloaders/DFU/BootloaderDFU.h
CamTrigUSB/Bootloaders/DFU/BootloaderDFU.txt
CamTrigUSB/Bootloaders/DFU/Descriptors.c
CamTrigUSB/Bootloaders/DFU/Descriptors.h
CamTrigUSB/Bootloaders/DFU/Doxygen.conf
CamTrigUSB/Bootloaders/DFU/makefile
CamTrigUSB/Bootloaders/TeensyHID/Descriptors.c
CamTrigUSB/Bootloaders/TeensyHID/Descriptors.h
CamTrigUSB/Bootloaders/TeensyHID/Doxygen.conf
CamTrigUSB/Bootloaders/TeensyHID/TeensyHID.c
CamTrigUSB/Bootloaders/TeensyHID/TeensyHID.h
CamTrigUSB/Bootloaders/TeensyHID/TeensyHID.txt
CamTrigUSB/Bootloaders/TeensyHID/makefile
CamTrigUSB/Demos/makefile
CamTrigUSB/Demos/AudioInput/AudioInput.aps
CamTrigUSB/Demos/AudioInput/AudioInput.c
CamTrigUSB/Demos/AudioInput/AudioInput.h
CamTrigUSB/Demos/AudioInput/AudioInput.txt
CamTrigUSB/Demos/AudioInput/Descriptors.c
CamTrigUSB/Demos/AudioInput/Descriptors.h
CamTrigUSB/Demos/AudioInput/Doxygen.conf
CamTrigUSB/Demos/AudioInput/makefile
CamTrigUSB/Demos/AudioOutput/AudioOutput.aps
CamTrigUSB/Demos/AudioOutput/AudioOutput.c
motmot.fview_ext_trig.egg-info/.gitignore
motmot.fview_ext_trig.egg-info/PKG-INFO
motmot.fview_ext_trig.egg-info/SOURCES.txt
motmot.fview_ext_trig.egg-info/dependency_links.txt
motmot.fview_ext_trig.egg-info/entry_points.txt
motmot.fview_ext_trig.egg-info/top_level.txt
