Metadata-Version: 1.0
Name: motmot.fview-ext-trig
Version: 0.4
Summary: Camera trigger device with precise timing and analog input
Home-page: http://code.astraw.com/projects/motmot/camtrig/motmot.fview_ext_trig/API.html
Author: Andrew Straw
Author-email: strawman@astraw.com
License: UNKNOWN
Platform: UNKNOWN
